utilset/Bitmap.py
utilset/dict.py
utilset/email.py
utilset/file.py
utilset/linkedin.py
utilset/list.py
utilset/string.py
utilset-0.0.5.dist-info/LICENSE
utilset-0.0.5.dist-info/METADATA
utilset-0.0.5.dist-info/WHEEL
utilset-0.0.5.dist-info/top_level.txt
utilset-0.0.5.dist-info/RECORD
