Metadata-Version: 2.1
Name: utilset
Version: 0.0.5
Summary: util sets
Home-page: https://github.com/puresai/utilset
Author: puresai
Author-email: sai210728@gmail.com
Platform: all
Classifier: Intended Audience :: Developers
Classifier: Operating System :: OS Independent
Classifier: Natural Language :: Chinese (Simplified)
Classifier: Programming Language :: Python :: 3.5
Classifier: Programming Language :: Python :: 3.6
Classifier: Programming Language :: Python :: 3.7
Classifier: Programming Language :: Python :: 3.8
Classifier: Topic :: Software Development :: Libraries
License-File: LICENSE
